mailmerge/__init__.py
mailmerge/__main__.py
mailmerge/exceptions.py
mailmerge/sendmail_client.py
mailmerge/template_message.py
mailmerge-2.3.0.dist-info/licenses/LICENSE
mailmerge-2.3.0.dist-info/METADATA
mailmerge-2.3.0.dist-info/WHEEL
mailmerge-2.3.0.dist-info/entry_points.txt
mailmerge-2.3.0.dist-info/top_level.txt
mailmerge-2.3.0.dist-info/RECORD
