Metadata-Version: 2.4
Name: mailmerge
Version: 2.3.0
Summary: A simple, command line mail merge tool
Author: Andrew DeOrio
Author-email: awdeorio@umich.edu
License: The MIT License (MIT)
Project-URL: homepage, https://github.com/awdeorio/mailmerge/
Keywords: mail merge,mailmerge,email
Requires-Python: >=3.10
License-File: LICENSE
Requires-Dist: click>=8.3
Requires-Dist: jinja2
Requires-Dist: markdown
Requires-Dist: html5lib
Provides-Extra: dev
Requires-Dist: twine; extra == "dev"
Requires-Dist: tox; extra == "dev"
Provides-Extra: test
Requires-Dist: check-manifest; extra == "test"
Requires-Dist: freezegun; extra == "test"
Requires-Dist: pycodestyle; extra == "test"
Requires-Dist: pydocstyle; extra == "test"
Requires-Dist: pylint; extra == "test"
Requires-Dist: pytest; extra == "test"
Requires-Dist: pytest-cov; extra == "test"
Requires-Dist: pytest-mock; extra == "test"
Dynamic: license-file
